diambra/diambra
diambra/__main__.py
diambra/__init__.py
